ezpylog/__init__.py
ezpylog-2.2.1.dist-info/LICENSE
ezpylog-2.2.1.dist-info/METADATA
ezpylog-2.2.1.dist-info/WHEEL
ezpylog-2.2.1.dist-info/top_level.txt
ezpylog-2.2.1.dist-info/RECORD
