Metadata-Version: 2.1
Name: ezpylog
Version: 2.2.1
Summary: A nice-looking, minimalist and easy-to-use Python library for logging your Python programs.
Home-page: https://github.com/JRodez/ezpylog
Author: Jérémie Rodez
Author-email: jeremierodez@outlook.com
License: GPLv3
Keywords: tool print ezpylog logger logging log level debug info warning error critical color terminal cli magnificient colorful beautiful filter filter_by_level filter_by_context filter_by_message
Classifier: Development Status :: 3 - Alpha
Classifier: Intended Audience :: Developers
Classifier: Topic :: Software Development
Classifier: License :: OSI Approved :: GNU General Public License v3 (GPLv3)
Classifier: Programming Language :: Python :: 3
Classifier: Programming Language :: Python :: 3.6
Classifier: Programming Language :: Python :: 3.7
Classifier: Programming Language :: Python :: 3.8
Classifier: Programming Language :: Python :: 3.9
Classifier: Programming Language :: Python :: 3.10
License-File: LICENSE
